enimation/__init__.py
enimation/loading.py
enimation/motions.py
enimation-0.1.5.dist-info/LICENSE
enimation-0.1.5.dist-info/METADATA
enimation-0.1.5.dist-info/WHEEL
enimation-0.1.5.dist-info/top_level.txt
enimation-0.1.5.dist-info/RECORD
