Metadata-Version: 2.1
Name: enimation
Version: 0.1.5
Summary: A customizable loading tool
Home-page: https://github.com/Kamanati/enimation
Author: Hasanfq
Author-email: hasanfq818@gmail.com
Classifier: Programming Language :: Python :: 3
Classifier: License :: OSI Approved :: MIT License
Classifier: Operating System :: OS Independent
Requires-Python: >=3.6
License-File: LICENSE
